qsafecrypto/__init__.py
qsafecrypto/aes_gcm_256.py
qsafecrypto/util.py
tests/__init__.py
tests/test_crypto.py
qsafecrypto-1.1.0.dist-info/LICENSE
qsafecrypto-1.1.0.dist-info/METADATA
qsafecrypto-1.1.0.dist-info/WHEEL
qsafecrypto-1.1.0.dist-info/top_level.txt
qsafecrypto-1.1.0.dist-info/RECORD
