Metadata-Version: 2.1
Name: qsafecrypto
Version: 1.1.0
Summary: A secure and user-friendly open-source cryptography library, offering modern cryptographic APIs that are resistant to quantum attacks. Protect your data with ease and confidence using advanced quantum-resistant algorithms
Home-page: https://github.com/mindreadio/qsafecrypto
Author: Md Fazlul Karim
Author-email: fazlulkarimrocky@gmail.com
Classifier: Programming Language :: Python :: 3
Classifier: License :: OSI Approved :: MIT License
Classifier: Operating System :: OS Independent
Requires-Python: >=3.7
License-File: LICENSE
Requires-Dist: based58 (>=0.1.1)
Requires-Dist: pycryptodome (>=3.17.0)
